HeXGButil/HeXGButil.cp39-win32.pyd
HeXGButil-0.1.0.dist-info/METADATA
HeXGButil-0.1.0.dist-info/WHEEL
HeXGButil-0.1.0.dist-info/top_level.txt
HeXGButil-0.1.0.dist-info/RECORD
