Metadata-Version: 2.1
Name: HeXGButil
Version: 0.1.0
Summary: numba functions needed for HEXGB
Home-page: https://zizdlp.com/spa
Author: xiaozi
Author-email: zdlp@sina.cn
License: BSD
Keywords: HeXGB
Classifier: Development Status :: 3 - Alpha
Classifier: Topic :: Utilities
Classifier: License :: OSI Approved :: BSD License
